mcp_calculator_kel/__init__.py
mcp_calculator_kel/__main__.py
mcp_calculator_kel/server.py
mcp_calculator_test-0.1.4.dist-info/METADATA
mcp_calculator_test-0.1.4.dist-info/WHEEL
mcp_calculator_test-0.1.4.dist-info/entry_points.txt
mcp_calculator_test-0.1.4.dist-info/RECORD
