Metadata-Version: 2.4
Name: mcp-calculator-test
Version: 0.1.4
Summary: Add your description here
Requires-Python: >=3.12
Requires-Dist: build>=1.3.0
Requires-Dist: mcp[cli]>=1.17.0
Requires-Dist: twine>=6.2.0
